[{"Name":"Dread Knot","Effect":"Burning Flames","Price":30.0,"Class":"Heavy","Item Type":"Cosmetic","Equip Region":"Regular","Grade":"No Grade","Unboxed From":"Old Series","Robo":false,"Generation":"First Gen","Effect Community Rating":4.59375,"Crate Cosmetic":true,"Months Since Last Price Update":9,"Effect Median Price":104.0,"Hat Median Price":14.0,"Hat Rating":-7.4,"Effect Rating":1.6,"Median Effect Rating":6.7375,"Median Hat Rating":-1.6,"GradeSize":"No Grade","Robo\/Misc\/Not":"Regular","Type of Crate Temp":false,"Type of Crate":"Category 2: Other Series","Crate Unboxed From":"Old Series","Halloween":"Category 1: Regular","Halloween Effect":"Category 1: Regular","Median Hat Price":14.0},{"Name":"Dread Knot","Effect":"Circling Heart","Price":null,"Class":"Heavy","Item Type":"Cosmetic","Equip Region":"Regular","Grade":"No Grade","Unboxed From":"Old Series","Robo":false,"Generation":"First Gen","Effect Community Rating":3.0625,"Crate Cosmetic":true,"Months Since Last Price Update":-1,"Effect Median Price":36.25,"Hat Median Price":14.0,"Hat Rating":null,"Effect Rating":null,"Median Effect Rating":0.45,"Median Hat Rating":-1.6,"GradeSize":"No Grade","Robo\/Misc\/Not":"Regular","Type of Crate Temp":false,"Type of Crate":"Category 2: Other Series","Crate Unboxed From":"Old Series","Halloween":"Category 1: Regular","Halloween Effect":"Category 1: Regular","Median Hat Price":14.0},{"Name":"Dread Knot","Effect":"Circling Peace Sign","Price":10.0,"Class":"Heavy","Item Type":"Cosmetic","Equip Region":"Regular","Grade":"No Grade","Unboxed From":"Old Series","Robo":false,"Generation":"First Gen","Effect Community Rating":2.21875,"Crate Cosmetic":true,"Months Since Last Price Update":21,"Effect Median Price":22.0,"Hat Median Price":14.0,"Hat Rating":-1.2,"Effect Rating":-0.4,"Median Effect Rating":-0.85,"Median Hat Rating":-1.6,"GradeSize":"No Grade","Robo\/Misc\/Not":"Regular","Type of Crate Temp":false,"Type of Crate":"Category 2: Other Series","Crate Unboxed From":"Old Series","Halloween":"Category 1: Regular","Halloween Effect":"Category 1: Regular","Median Hat Price":14.0},{"Name":"Dread Knot","Effect":"Circling TF Logo","Price":9.0,"Class":"Heavy","Item Type":"Cosmetic","Equip Region":"Regular","Grade":"No Grade","Unboxed From":"Old Series","Robo":false,"Generation":"First Gen","Effect Community Rating":2.34375,"Crate Cosmetic":true,"Months Since Last Price Update":44,"Effect Median Price":21.5,"Hat Median Price":14.0,"Hat Rating":-1.25,"Effect Rating":-0.5,"Median Effect Rating":-0.9125,"Median Hat Rating":-1.6,"GradeSize":"No Grade","Robo\/Misc\/Not":"Regular","Type of Crate Temp":false,"Type of Crate":"Category 2: Other Series","Crate Unboxed From":"Old Series","Halloween":"Category 1: Regular","Halloween Effect":"Category 1: Regular","Median Hat Price":14.0},{"Name":"Dread Knot","Effect":"Green Confetti","Price":9.0,"Class":"Heavy","Item Type":"Cosmetic","Equip Region":"Regular","Grade":"No Grade","Unboxed From":"Old Series","Robo":false,"Generation":"First Gen","Effect Community Rating":1.40625,"Crate Cosmetic":true,"Months Since Last Price Update":15,"Effect Median Price":17.0,"Hat Median Price":14.0,"Hat Rating":-0.8,"Effect Rating":-0.5,"Median Effect Rating":-1.375,"Median Hat Rating":-1.6,"GradeSize":"No Grade","Robo\/Misc\/Not":"Regular","Type of Crate Temp":false,"Type of Crate":"Category 2: Other Series","Crate Unboxed From":"Old Series","Halloween":"Category 1: Regular","Halloween Effect":"Category 1: Regular","Median Hat Price":14.0},{"Name":"Dread Knot","Effect":"Green Energy","Price":15.0,"Class":"Heavy","Item Type":"Cosmetic","Equip Region":"Regular","Grade":"No Grade","Unboxed From":"Old Series","Robo":false,"Generation":"First Gen","Effect Community Rating":4.15625,"Crate Cosmetic":true,"Months Since Last Price Update":15,"Effect Median Price":50.0,"Hat Median Price":14.0,"Hat Rating":-3.5,"Effect Rating":0.1,"Median Effect Rating":1.8375,"Median Hat Rating":-1.6,"GradeSize":"No Grade","Robo\/Misc\/Not":"Regular","Type of Crate Temp":false,"Type of Crate":"Category 2: Other Series","Crate Unboxed From":"Old Series","Halloween":"Category 1: Regular","Halloween Effect":"Category 1: Regular","Median Hat Price":14.0},{"Name":"Dread Knot","Effect":"Haunted Ghosts","Price":12.0,"Class":"Heavy","Item Type":"Cosmetic","Equip Region":"Regular","Grade":"No Grade","Unboxed From":"Old Series","Robo":false,"Generation":"First Gen","Effect Community Rating":3.03125,"Crate Cosmetic":true,"Months Since Last Price Update":33,"Effect Median Price":35.0,"Hat Median Price":14.0,"Hat Rating":-2.3,"Effect Rating":-0.2,"Median Effect Rating":0.325,"Median Hat Rating":-1.6,"GradeSize":"No Grade","Robo\/Misc\/Not":"Regular","Type of Crate Temp":false,"Type of Crate":"Category 2: Other Series","Crate Unboxed From":"Old Series","Halloween":"Category 1: Regular","Halloween Effect":"Category 1: Regular","Median Hat Price":14.0},{"Name":"Dread Knot","Effect":"Massed Flies","Price":8.5,"Class":"Heavy","Item Type":"Cosmetic","Equip Region":"Regular","Grade":"No Grade","Unboxed From":"Old Series","Robo":false,"Generation":"First Gen","Effect Community Rating":0.1875,"Crate Cosmetic":true,"Months Since Last Price Update":8,"Effect Median Price":13.5,"Hat Median Price":14.0,"Hat Rating":-0.5,"Effect Rating":-0.55,"Median Effect Rating":-1.7,"Median Hat Rating":-1.6,"GradeSize":"No Grade","Robo\/Misc\/Not":"Regular","Type of Crate Temp":false,"Type of Crate":"Category 2: Other Series","Crate Unboxed From":"Old Series","Halloween":"Category 1: Regular","Halloween Effect":"Category 1: Regular","Median Hat Price":14.0},{"Name":"Dread Knot","Effect":"Purple Confetti","Price":null,"Class":"Heavy","Item Type":"Cosmetic","Equip Region":"Regular","Grade":"No Grade","Unboxed From":"Old Series","Robo":false,"Generation":"First Gen","Effect Community Rating":1.34375,"Crate Cosmetic":true,"Months Since Last Price Update":-1,"Effect Median Price":18.0,"Hat Median Price":14.0,"Hat Rating":null,"Effect Rating":null,"Median Effect Rating":-1.25,"Median Hat Rating":-1.6,"GradeSize":"No Grade","Robo\/Misc\/Not":"Regular","Type of Crate Temp":false,"Type of Crate":"Category 2: Other Series","Crate Unboxed From":"Old Series","Halloween":"Category 1: Regular","Halloween Effect":"Category 1: Regular","Median Hat Price":14.0},{"Name":"Dread Knot","Effect":"Purple Energy","Price":19.0,"Class":"Heavy","Item Type":"Cosmetic","Equip Region":"Regular","Grade":"No Grade","Unboxed From":"Old Series","Robo":false,"Generation":"First Gen","Effect Community Rating":4.21875,"Crate Cosmetic":true,"Months Since Last Price Update":2,"Effect Median Price":55.0,"Hat Median Price":14.0,"Hat Rating":-3.6,"Effect Rating":0.5,"Median Effect Rating":2.125,"Median Hat Rating":-1.6,"GradeSize":"No Grade","Robo\/Misc\/Not":"Regular","Type of Crate Temp":false,"Type of Crate":"Category 2: Other Series","Crate Unboxed From":"Old Series","Halloween":"Category 1: Regular","Halloween Effect":"Category 1: Regular","Median Hat Price":14.0},{"Name":"Dread Knot","Effect":"Scorching Flames","Price":33.0,"Class":"Heavy","Item Type":"Cosmetic","Equip Region":"Regular","Grade":"No Grade","Unboxed From":"Old Series","Robo":false,"Generation":"First Gen","Effect Community Rating":4.625,"Crate Cosmetic":true,"Months Since Last Price Update":8,"Effect Median Price":92.5,"Hat Median Price":14.0,"Hat Rating":-5.95,"Effect Rating":1.9,"Median Effect Rating":5.9,"Median Hat Rating":-1.6,"GradeSize":"No Grade","Robo\/Misc\/Not":"Regular","Type of Crate Temp":false,"Type of Crate":"Category 2: Other Series","Crate Unboxed From":"Old Series","Halloween":"Category 1: Regular","Halloween Effect":"Category 1: Regular","Median Hat Price":14.0},{"Name":"Dread Knot","Effect":"Searing Plasma","Price":9.5,"Class":"Heavy","Item Type":"Cosmetic","Equip Region":"Regular","Grade":"No Grade","Unboxed From":"Old Series","Robo":false,"Generation":"First Gen","Effect Community Rating":2.6875,"Crate Cosmetic":true,"Months Since Last Price Update":19,"Effect Median Price":28.0,"Hat Median Price":14.0,"Hat Rating":-1.85,"Effect Rating":-0.45,"Median Effect Rating":-0.45,"Median Hat Rating":-1.6,"GradeSize":"No Grade","Robo\/Misc\/Not":"Regular","Type of Crate Temp":false,"Type of Crate":"Category 2: Other Series","Crate Unboxed From":"Old Series","Halloween":"Category 1: Regular","Halloween Effect":"Category 1: Regular","Median Hat Price":14.0},{"Name":"Dread Knot","Effect":"Sunbeams","Price":26.0,"Class":"Heavy","Item Type":"Cosmetic","Equip Region":"Regular","Grade":"No Grade","Unboxed From":"Old Series","Robo":false,"Generation":"First Gen","Effect Community Rating":4.3125,"Crate Cosmetic":true,"Months Since Last Price Update":19,"Effect Median Price":84.0,"Hat Median Price":14.0,"Hat Rating":-5.8,"Effect Rating":1.2,"Median Effect Rating":4.9,"Median Hat Rating":-1.6,"GradeSize":"No Grade","Robo\/Misc\/Not":"Regular","Type of Crate Temp":false,"Type of Crate":"Category 2: Other Series","Crate Unboxed From":"Old Series","Halloween":"Category 1: Regular","Halloween Effect":"Category 1: Regular","Median Hat Price":14.0},{"Name":"Dread Knot","Effect":"Vivid Plasma","Price":14.0,"Class":"Heavy","Item Type":"Cosmetic","Equip Region":"Regular","Grade":"No Grade","Unboxed From":"Old Series","Robo":false,"Generation":"First Gen","Effect Community Rating":2.875,"Crate Cosmetic":true,"Months Since Last Price Update":23,"Effect Median Price":30.0,"Hat Median Price":14.0,"Hat Rating":-1.6,"Effect Rating":0.0,"Median Effect Rating":-0.0625,"Median Hat Rating":-1.6,"GradeSize":"No Grade","Robo\/Misc\/Not":"Regular","Type of Crate Temp":false,"Type of Crate":"Category 2: Other Series","Crate Unboxed From":"Old Series","Halloween":"Category 1: Regular","Halloween Effect":"Category 1: Regular","Median Hat Price":14.0},{"Name":"Dread Knot","Effect":"Blizzardy Storm","Price":8.5,"Class":"Heavy","Item Type":"Cosmetic","Equip Region":"Regular","Grade":"No Grade","Unboxed From":"Old Series","Robo":false,"Generation":"Second Gen","Effect Community Rating":3.15625,"Crate Cosmetic":true,"Months Since Last Price Update":1,"Effect Median Price":18.25,"Hat Median Price":14.0,"Hat Rating":-0.975,"Effect Rating":-0.55,"Median Effect Rating":-1.15,"Median Hat Rating":-1.6,"GradeSize":"No Grade","Robo\/Misc\/Not":"Regular","Type of Crate Temp":false,"Type of Crate":"Category 2: Other Series","Crate Unboxed From":"Old Series","Halloween":"Category 1: Regular","Halloween Effect":"Category 1: Regular","Median Hat Price":14.0},{"Name":"Dread Knot","Effect":"Bubbling","Price":8.5,"Class":"Heavy","Item Type":"Cosmetic","Equip Region":"Regular","Grade":"No Grade","Unboxed From":"Old Series","Robo":false,"Generation":"Second Gen","Effect Community Rating":1.4375,"Crate Cosmetic":true,"Months Since Last Price Update":15,"Effect Median Price":13.0,"Hat Median Price":14.0,"Hat Rating":-0.45,"Effect Rating":-0.55,"Median Effect Rating":-1.7,"Median Hat Rating":-1.6,"GradeSize":"No Grade","Robo\/Misc\/Not":"Regular","Type of Crate Temp":false,"Type of Crate":"Category 2: Other Series","Crate Unboxed From":"Old Series","Halloween":"Category 1: Regular","Halloween Effect":"Category 1: Regular","Median Hat Price":14.0},{"Name":"Dread Knot","Effect":"Nuts n' Bolts","Price":9.5,"Class":"Heavy","Item Type":"Cosmetic","Equip Region":"Regular","Grade":"No Grade","Unboxed From":"Old Series","Robo":false,"Generation":"Second Gen","Effect Community Rating":0.4375,"Crate Cosmetic":true,"Months Since Last Price Update":21,"Effect Median Price":12.0,"Hat Median Price":14.0,"Hat Rating":-0.25,"Effect Rating":-0.45,"Median Effect Rating":-1.85,"Median Hat Rating":-1.6,"GradeSize":"No Grade","Robo\/Misc\/Not":"Regular","Type of Crate Temp":false,"Type of Crate":"Category 2: Other Series","Crate Unboxed From":"Old Series","Halloween":"Category 1: Regular","Halloween Effect":"Category 1: Regular","Median Hat Price":14.0},{"Name":"Dread Knot","Effect":"Orbiting Fire","Price":9.0,"Class":"Heavy","Item Type":"Cosmetic","Equip Region":"Regular","Grade":"No Grade","Unboxed From":"Old Series","Robo":false,"Generation":"Second Gen","Effect Community Rating":1.625,"Crate Cosmetic":true,"Months Since Last Price Update":21,"Effect Median Price":17.0,"Hat Median Price":14.0,"Hat Rating":-0.8,"Effect Rating":-0.5,"Median Effect Rating":-1.5,"Median Hat Rating":-1.6,"GradeSize":"No Grade","Robo\/Misc\/Not":"Regular","Type of Crate Temp":false,"Type of Crate":"Category 2: Other Series","Crate Unboxed From":"Old Series","Halloween":"Category 1: Regular","Halloween Effect":"Category 1: Regular","Median Hat Price":14.0},{"Name":"Dread Knot","Effect":"Orbiting Planets","Price":null,"Class":"Heavy","Item Type":"Cosmetic","Equip Region":"Regular","Grade":"No Grade","Unboxed From":"Old Series","Robo":false,"Generation":"Second Gen","Effect Community Rating":1.09375,"Crate Cosmetic":true,"Months Since Last Price Update":-1,"Effect Median Price":13.0,"Hat Median Price":14.0,"Hat Rating":null,"Effect Rating":null,"Median Effect Rating":-1.75,"Median Hat Rating":-1.6,"GradeSize":"No Grade","Robo\/Misc\/Not":"Regular","Type of Crate Temp":false,"Type of Crate":"Category 2: Other Series","Crate Unboxed From":"Old Series","Halloween":"Category 1: Regular","Halloween Effect":"Category 1: Regular","Median Hat Price":14.0},{"Name":"Dread Knot","Effect":"Smoking","Price":7.5,"Class":"Heavy","Item Type":"Cosmetic","Equip Region":"Regular","Grade":"No Grade","Unboxed From":"Old Series","Robo":false,"Generation":"Second Gen","Effect Community Rating":2.0,"Crate Cosmetic":true,"Months Since Last Price Update":8,"Effect Median Price":14.0,"Hat Median Price":14.0,"Hat Rating":-0.65,"Effect Rating":-0.65,"Median Effect Rating":-1.6,"Median Hat Rating":-1.6,"GradeSize":"No Grade","Robo\/Misc\/Not":"Regular","Type of Crate Temp":false,"Type of Crate":"Category 2: Other Series","Crate Unboxed From":"Old Series","Halloween":"Category 1: Regular","Halloween Effect":"Category 1: Regular","Median Hat Price":14.0},{"Name":"Dread Knot","Effect":"Steaming","Price":7.75,"Class":"Heavy","Item Type":"Cosmetic","Equip Region":"Regular","Grade":"No Grade","Unboxed From":"Old Series","Robo":false,"Generation":"Second Gen","Effect Community Rating":1.90625,"Crate Cosmetic":true,"Months Since Last Price Update":11,"Effect Median Price":13.5,"Hat Median Price":14.0,"Hat Rating":-0.575,"Effect Rating":-0.625,"Median Effect Rating":-1.675,"Median Hat Rating":-1.6,"GradeSize":"No Grade","Robo\/Misc\/Not":"Regular","Type of Crate Temp":false,"Type of Crate":"Category 2: Other Series","Crate Unboxed From":"Old Series","Halloween":"Category 1: Regular","Halloween Effect":"Category 1: Regular","Median Hat Price":14.0},{"Name":"Dread Knot","Effect":"Stormy Storm","Price":8.5,"Class":"Heavy","Item Type":"Cosmetic","Equip Region":"Regular","Grade":"No Grade","Unboxed From":"Old Series","Robo":false,"Generation":"Second Gen","Effect Community Rating":2.8125,"Crate Cosmetic":true,"Months Since Last Price Update":21,"Effect Median Price":18.0,"Hat Median Price":14.0,"Hat Rating":-0.95,"Effect Rating":-0.55,"Median Effect Rating":-1.225,"Median Hat Rating":-1.6,"GradeSize":"No Grade","Robo\/Misc\/Not":"Regular","Type of Crate Temp":false,"Type of Crate":"Category 2: Other Series","Crate Unboxed From":"Old Series","Halloween":"Category 1: Regular","Halloween Effect":"Category 1: Regular","Median Hat Price":14.0},{"Name":"Dread Knot","Effect":"Aces High","Price":8.5,"Class":"Heavy","Item Type":"Cosmetic","Equip Region":"Regular","Grade":"No Grade","Unboxed From":"Old Series","Robo":false,"Generation":"Third Gen","Effect Community Rating":1.46875,"Crate Cosmetic":true,"Months Since Last Price Update":15,"Effect Median Price":14.0,"Hat Median Price":14.0,"Hat Rating":-0.55,"Effect Rating":-0.55,"Median Effect Rating":-1.7,"Median Hat Rating":-1.6,"GradeSize":"No Grade","Robo\/Misc\/Not":"Regular","Type of Crate Temp":false,"Type of Crate":"Category 2: Other Series","Crate Unboxed From":"Old Series","Halloween":"Category 1: Regular","Halloween Effect":"Category 1: Regular","Median Hat Price":14.0},{"Name":"Dread Knot","Effect":"Cloud 9","Price":9.25,"Class":"Heavy","Item Type":"Cosmetic","Equip Region":"Regular","Grade":"No Grade","Unboxed From":"Old Series","Robo":false,"Generation":"Third Gen","Effect Community Rating":2.625,"Crate Cosmetic":true,"Months Since Last Price Update":6,"Effect Median Price":22.5,"Hat Median Price":14.0,"Hat Rating":-1.325,"Effect Rating":-0.475,"Median Effect Rating":-0.85,"Median Hat Rating":-1.6,"GradeSize":"No Grade","Robo\/Misc\/Not":"Regular","Type of Crate Temp":false,"Type of Crate":"Category 2: Other Series","Crate Unboxed From":"Old Series","Halloween":"Category 1: Regular","Halloween Effect":"Category 1: Regular","Median Hat Price":14.0},{"Name":"Dread Knot","Effect":"Dead Presidents","Price":8.5,"Class":"Heavy","Item Type":"Cosmetic","Equip Region":"Regular","Grade":"No Grade","Unboxed From":"Old Series","Robo":false,"Generation":"Third Gen","Effect Community Rating":1.125,"Crate Cosmetic":true,"Months Since Last Price Update":23,"Effect Median Price":15.0,"Hat Median Price":14.0,"Hat Rating":-0.65,"Effect Rating":-0.55,"Median Effect Rating":-1.6,"Median Hat Rating":-1.6,"GradeSize":"No Grade","Robo\/Misc\/Not":"Regular","Type of Crate Temp":false,"Type of Crate":"Category 2: Other Series","Crate Unboxed From":"Old Series","Halloween":"Category 1: Regular","Halloween Effect":"Category 1: Regular","Median Hat Price":14.0},{"Name":"Dread Knot","Effect":"Disco Beat Down","Price":10.5,"Class":"Heavy","Item Type":"Cosmetic","Equip Region":"Regular","Grade":"No Grade","Unboxed From":"Old Series","Robo":false,"Generation":"Third Gen","Effect Community Rating":3.53125,"Crate Cosmetic":true,"Months Since Last Price Update":2,"Effect Median Price":26.5,"Hat Median Price":14.0,"Hat Rating":-1.6,"Effect Rating":-0.35,"Median Effect Rating":-0.35,"Median Hat Rating":-1.6,"GradeSize":"No Grade","Robo\/Misc\/Not":"Regular","Type of Crate Temp":false,"Type of Crate":"Category 2: Other Series","Crate Unboxed From":"Old Series","Halloween":"Category 1: Regular","Halloween Effect":"Category 1: Regular","Median Hat Price":14.0},{"Name":"Dread Knot","Effect":"Kill-a-Watt","Price":8.5,"Class":"Heavy","Item Type":"Cosmetic","Equip Region":"Regular","Grade":"No Grade","Unboxed From":"Old Series","Robo":false,"Generation":"Third Gen","Effect Community Rating":2.15625,"Crate Cosmetic":true,"Months Since Last Price Update":22,"Effect Median Price":17.25,"Hat Median Price":14.0,"Hat Rating":-0.875,"Effect Rating":-0.55,"Median Effect Rating":-1.3,"Median Hat Rating":-1.6,"GradeSize":"No Grade","Robo\/Misc\/Not":"Regular","Type of Crate Temp":false,"Type of Crate":"Category 2: Other Series","Crate Unboxed From":"Old Series","Halloween":"Category 1: Regular","Halloween Effect":"Category 1: Regular","Median Hat Price":14.0},{"Name":"Dread Knot","Effect":"Miami Nights","Price":10.5,"Class":"Heavy","Item Type":"Cosmetic","Equip Region":"Regular","Grade":"No Grade","Unboxed From":"Old Series","Robo":false,"Generation":"Third Gen","Effect Community Rating":2.90625,"Crate Cosmetic":true,"Months Since Last Price Update":23,"Effect Median Price":21.0,"Hat Median Price":14.0,"Hat Rating":-1.05,"Effect Rating":-0.35,"Median Effect Rating":-1.0,"Median Hat Rating":-1.6,"GradeSize":"No Grade","Robo\/Misc\/Not":"Regular","Type of Crate Temp":false,"Type of Crate":"Category 2: Other Series","Crate Unboxed From":"Old Series","Halloween":"Category 1: Regular","Halloween Effect":"Category 1: Regular","Median Hat Price":14.0},{"Name":"Dread Knot","Effect":"Terror-Watt","Price":10.0,"Class":"Heavy","Item Type":"Cosmetic","Equip Region":"Regular","Grade":"No Grade","Unboxed From":"Old Series","Robo":false,"Generation":"Third Gen","Effect Community Rating":2.125,"Crate Cosmetic":true,"Months Since Last Price Update":15,"Effect Median Price":18.0,"Hat Median Price":14.0,"Hat Rating":-0.8,"Effect Rating":-0.4,"Median Effect Rating":-1.2,"Median Hat Rating":-1.6,"GradeSize":"No Grade","Robo\/Misc\/Not":"Regular","Type of Crate Temp":false,"Type of Crate":"Category 2: Other Series","Crate Unboxed From":"Old Series","Halloween":"Category 1: Regular","Halloween Effect":"Category 1: Regular","Median Hat Price":14.0},{"Name":"Dread Knot","Effect":"Cauldron Bubbles","Price":16.0,"Class":"Heavy","Item Type":"Cosmetic","Equip Region":"Regular","Grade":"No Grade","Unboxed From":"Old Series","Robo":false,"Generation":"Halloween 2011","Effect Community Rating":1.59375,"Crate Cosmetic":true,"Months Since Last Price Update":9,"Effect Median Price":32.0,"Hat Median Price":14.0,"Hat Rating":-1.6,"Effect Rating":0.2,"Median Effect Rating":0.1125,"Median Hat Rating":-1.6,"GradeSize":"No Grade","Robo\/Misc\/Not":"Regular","Type of Crate Temp":false,"Type of Crate":"Category 2: Other Series","Crate Unboxed From":"Old Series","Halloween":"Category 2: Halloween","Halloween Effect":"Category 2: Halloween","Median Hat Price":14.0},{"Name":"Dread Knot","Effect":"Cloudy Moon","Price":35.0,"Class":"Heavy","Item Type":"Cosmetic","Equip Region":"Regular","Grade":"No Grade","Unboxed From":"Old Series","Robo":false,"Generation":"Halloween 2011","Effect Community Rating":4.125,"Crate Cosmetic":true,"Months Since Last Price Update":5,"Effect Median Price":92.5,"Hat Median Price":14.0,"Hat Rating":-5.75,"Effect Rating":2.1,"Median Effect Rating":5.7,"Median Hat Rating":-1.6,"GradeSize":"No Grade","Robo\/Misc\/Not":"Regular","Type of Crate Temp":false,"Type of Crate":"Category 2: Other Series","Crate Unboxed From":"Old Series","Halloween":"Category 2: Halloween","Halloween Effect":"Category 2: Halloween","Median Hat Price":14.0},{"Name":"Dread Knot","Effect":"Eerie Orbiting Fire","Price":14.0,"Class":"Heavy","Item Type":"Cosmetic","Equip Region":"Regular","Grade":"No Grade","Unboxed From":"Old Series","Robo":false,"Generation":"Halloween 2011","Effect Community Rating":1.6875,"Crate Cosmetic":true,"Months Since Last Price Update":1,"Effect Median Price":30.25,"Hat Median Price":14.0,"Hat Rating":-1.625,"Effect Rating":0.0,"Median Effect Rating":-0.2,"Median Hat Rating":-1.6,"GradeSize":"No Grade","Robo\/Misc\/Not":"Regular","Type of Crate Temp":false,"Type of Crate":"Category 2: Other Series","Crate Unboxed From":"Old Series","Halloween":"Category 2: Halloween","Halloween Effect":"Category 2: Halloween","Median Hat Price":14.0},{"Name":"Dread Knot","Effect":"Flaming Lantern","Price":14.0,"Class":"Heavy","Item Type":"Cosmetic","Equip Region":"Regular","Grade":"No Grade","Unboxed From":"Old Series","Robo":false,"Generation":"Halloween 2011","Effect Community Rating":1.9375,"Crate Cosmetic":true,"Months Since Last Price Update":21,"Effect Median Price":36.0,"Hat Median Price":14.0,"Hat Rating":-2.2,"Effect Rating":0.0,"Median Effect Rating":0.3,"Median Hat Rating":-1.6,"GradeSize":"No Grade","Robo\/Misc\/Not":"Regular","Type of Crate Temp":false,"Type of Crate":"Category 2: Other Series","Crate Unboxed From":"Old Series","Halloween":"Category 2: Halloween","Halloween Effect":"Category 2: Halloween","Median Hat Price":14.0},{"Name":"Dread Knot","Effect":"Harvest Moon","Price":null,"Class":"Heavy","Item Type":"Cosmetic","Equip Region":"Regular","Grade":"No Grade","Unboxed From":"Old Series","Robo":false,"Generation":"Halloween 2012","Effect Community Rating":4.0,"Crate Cosmetic":true,"Months Since Last Price Update":-1,"Effect Median Price":110.0,"Hat Median Price":14.0,"Hat Rating":null,"Effect Rating":null,"Median Effect Rating":7.55,"Median Hat Rating":-1.6,"GradeSize":"No Grade","Robo\/Misc\/Not":"Regular","Type of Crate Temp":false,"Type of Crate":"Category 2: Other Series","Crate Unboxed From":"Old Series","Halloween":"Category 2: Halloween","Halloween Effect":"Category 2: Halloween","Median Hat Price":14.0},{"Name":"Dread Knot","Effect":"It's A Secret To Everybody","Price":null,"Class":"Heavy","Item Type":"Cosmetic","Equip Region":"Regular","Grade":"No Grade","Unboxed From":"Old Series","Robo":false,"Generation":"Halloween 2012","Effect Community Rating":4.1875,"Crate Cosmetic":true,"Months Since Last Price Update":-1,"Effect Median Price":106.75,"Hat Median Price":14.0,"Hat Rating":null,"Effect Rating":null,"Median Effect Rating":7.575,"Median Hat Rating":-1.6,"GradeSize":"No Grade","Robo\/Misc\/Not":"Regular","Type of Crate Temp":false,"Type of Crate":"Category 2: Other Series","Crate Unboxed From":"Old Series","Halloween":"Category 2: Halloween","Halloween Effect":"Category 2: Halloween","Median Hat Price":14.0},{"Name":"Dread Knot","Effect":"Knifestorm","Price":39.0,"Class":"Heavy","Item Type":"Cosmetic","Equip Region":"Regular","Grade":"No Grade","Unboxed From":"Old Series","Robo":false,"Generation":"Halloween 2012","Effect Community Rating":4.09375,"Crate Cosmetic":true,"Months Since Last Price Update":10,"Effect Median Price":97.5,"Hat Median Price":14.0,"Hat Rating":-5.85,"Effect Rating":2.5,"Median Effect Rating":6.3,"Median Hat Rating":-1.6,"GradeSize":"No Grade","Robo\/Misc\/Not":"Regular","Type of Crate Temp":false,"Type of Crate":"Category 2: Other Series","Crate Unboxed From":"Old Series","Halloween":"Category 2: Halloween","Halloween Effect":"Category 2: Halloween","Median Hat Price":14.0},{"Name":"Dread Knot","Effect":"Misty Skull","Price":26.0,"Class":"Heavy","Item Type":"Cosmetic","Equip Region":"Regular","Grade":"No Grade","Unboxed From":"Old Series","Robo":false,"Generation":"Halloween 2012","Effect Community Rating":3.90625,"Crate Cosmetic":true,"Months Since Last Price Update":20,"Effect Median Price":70.0,"Hat Median Price":14.0,"Hat Rating":-4.4,"Effect Rating":1.2,"Median Effect Rating":3.8875,"Median Hat Rating":-1.6,"GradeSize":"No Grade","Robo\/Misc\/Not":"Regular","Type of Crate Temp":false,"Type of Crate":"Category 2: Other Series","Crate Unboxed From":"Old Series","Halloween":"Category 2: Halloween","Halloween Effect":"Category 2: Halloween","Median Hat Price":14.0},{"Name":"Dread Knot","Effect":"Stormy 13th Hour","Price":34.0,"Class":"Heavy","Item Type":"Cosmetic","Equip Region":"Regular","Grade":"No Grade","Unboxed From":"Old Series","Robo":false,"Generation":"Halloween 2012","Effect Community Rating":4.21875,"Crate Cosmetic":true,"Months Since Last Price Update":25,"Effect Median Price":100.0,"Hat Median Price":14.0,"Hat Rating":-6.6,"Effect Rating":2.0,"Median Effect Rating":6.0625,"Median Hat Rating":-1.6,"GradeSize":"No Grade","Robo\/Misc\/Not":"Regular","Type of Crate Temp":false,"Type of Crate":"Category 2: Other Series","Crate Unboxed From":"Old Series","Halloween":"Category 2: Halloween","Halloween Effect":"Category 2: Halloween","Median Hat Price":14.0},{"Name":"Dread Knot","Effect":"Arcana","Price":null,"Class":"Heavy","Item Type":"Cosmetic","Equip Region":"Regular","Grade":"No Grade","Unboxed From":"Old Series","Robo":false,"Generation":"Halloween 2013","Effect Community Rating":4.1875,"Crate Cosmetic":true,"Months Since Last Price Update":-1,"Effect Median Price":120.0,"Hat Median Price":14.0,"Hat Rating":null,"Effect Rating":null,"Median Effect Rating":8.5,"Median Hat Rating":-1.6,"GradeSize":"No Grade","Robo\/Misc\/Not":"Regular","Type of Crate Temp":false,"Type of Crate":"Category 2: Other Series","Crate Unboxed From":"Old Series","Halloween":"Category 2: Halloween","Halloween Effect":"Category 2: Halloween","Median Hat Price":14.0},{"Name":"Dread Knot","Effect":"Chiroptera Venenata","Price":null,"Class":"Heavy","Item Type":"Cosmetic","Equip Region":"Regular","Grade":"No Grade","Unboxed From":"Old Series","Robo":false,"Generation":"Halloween 2013","Effect Community Rating":3.65625,"Crate Cosmetic":true,"Months Since Last Price Update":-1,"Effect Median Price":80.0,"Hat Median Price":14.0,"Hat Rating":null,"Effect Rating":null,"Median Effect Rating":4.85,"Median Hat Rating":-1.6,"GradeSize":"No Grade","Robo\/Misc\/Not":"Regular","Type of Crate Temp":false,"Type of Crate":"Category 2: Other Series","Crate Unboxed From":"Old Series","Halloween":"Category 2: Halloween","Halloween Effect":"Category 2: Halloween","Median Hat Price":14.0},{"Name":"Dread Knot","Effect":"Darkblaze","Price":null,"Class":"Heavy","Item Type":"Cosmetic","Equip Region":"Regular","Grade":"No Grade","Unboxed From":"Old Series","Robo":false,"Generation":"Halloween 2013","Effect Community Rating":4.0,"Crate Cosmetic":true,"Months Since Last Price Update":-1,"Effect Median Price":100.0,"Hat Median Price":14.0,"Hat Rating":null,"Effect Rating":null,"Median Effect Rating":6.4,"Median Hat Rating":-1.6,"GradeSize":"No Grade","Robo\/Misc\/Not":"Regular","Type of Crate Temp":false,"Type of Crate":"Category 2: Other Series","Crate Unboxed From":"Old Series","Halloween":"Category 2: Halloween","Halloween Effect":"Category 2: Halloween","Median Hat Price":14.0},{"Name":"Dread Knot","Effect":"Demonflame","Price":40.0,"Class":"Heavy","Item Type":"Cosmetic","Equip Region":"Regular","Grade":"No Grade","Unboxed From":"Old Series","Robo":false,"Generation":"Halloween 2013","Effect Community Rating":3.96875,"Crate Cosmetic":true,"Months Since Last Price Update":29,"Effect Median Price":95.0,"Hat Median Price":14.0,"Hat Rating":-5.5,"Effect Rating":2.6,"Median Effect Rating":6.1,"Median Hat Rating":-1.6,"GradeSize":"No Grade","Robo\/Misc\/Not":"Regular","Type of Crate Temp":false,"Type of Crate":"Category 2: Other Series","Crate Unboxed From":"Old Series","Halloween":"Category 2: Halloween","Halloween Effect":"Category 2: Halloween","Median Hat Price":14.0},{"Name":"Dread Knot","Effect":"Hellfire","Price":null,"Class":"Heavy","Item Type":"Cosmetic","Equip Region":"Regular","Grade":"No Grade","Unboxed From":"Old Series","Robo":false,"Generation":"Halloween 2013","Effect Community Rating":4.0625,"Crate Cosmetic":true,"Months Since Last Price Update":-1,"Effect Median Price":92.0,"Hat Median Price":14.0,"Hat Rating":null,"Effect Rating":null,"Median Effect Rating":6.35,"Median Hat Rating":-1.6,"GradeSize":"No Grade","Robo\/Misc\/Not":"Regular","Type of Crate Temp":false,"Type of Crate":"Category 2: Other Series","Crate Unboxed From":"Old Series","Halloween":"Category 2: Halloween","Halloween Effect":"Category 2: Halloween","Median Hat Price":14.0},{"Name":"Dread Knot","Effect":"Poisoned Shadows","Price":null,"Class":"Heavy","Item Type":"Cosmetic","Equip Region":"Regular","Grade":"No Grade","Unboxed From":"Old Series","Robo":false,"Generation":"Halloween 2013","Effect Community Rating":3.875,"Crate Cosmetic":true,"Months Since Last Price Update":-1,"Effect Median Price":103.5,"Hat Median Price":14.0,"Hat Rating":null,"Effect Rating":null,"Median Effect Rating":7.1,"Median Hat Rating":-1.6,"GradeSize":"No Grade","Robo\/Misc\/Not":"Regular","Type of Crate Temp":false,"Type of Crate":"Category 2: Other Series","Crate Unboxed From":"Old Series","Halloween":"Category 2: Halloween","Halloween Effect":"Category 2: Halloween","Median Hat Price":14.0},{"Name":"Dread Knot","Effect":"Something Burning This Way Comes","Price":null,"Class":"Heavy","Item Type":"Cosmetic","Equip Region":"Regular","Grade":"No Grade","Unboxed From":"Old Series","Robo":false,"Generation":"Halloween 2013","Effect Community Rating":3.6875,"Crate Cosmetic":true,"Months Since Last Price Update":-1,"Effect Median Price":80.0,"Hat Median Price":14.0,"Hat Rating":null,"Effect Rating":null,"Median Effect Rating":4.55,"Median Hat Rating":-1.6,"GradeSize":"No Grade","Robo\/Misc\/Not":"Regular","Type of Crate Temp":false,"Type of Crate":"Category 2: Other Series","Crate Unboxed From":"Old Series","Halloween":"Category 2: Halloween","Halloween Effect":"Category 2: Halloween","Median Hat Price":14.0},{"Name":"Dread Knot","Effect":"Spellbound","Price":null,"Class":"Heavy","Item Type":"Cosmetic","Equip Region":"Regular","Grade":"No Grade","Unboxed From":"Old Series","Robo":false,"Generation":"Halloween 2013","Effect Community Rating":4.3125,"Crate Cosmetic":true,"Months Since Last Price Update":-1,"Effect Median Price":140.0,"Hat Median Price":14.0,"Hat Rating":null,"Effect Rating":null,"Median Effect Rating":10.75,"Median Hat Rating":-1.6,"GradeSize":"No Grade","Robo\/Misc\/Not":"Regular","Type of Crate Temp":false,"Type of Crate":"Category 2: Other Series","Crate Unboxed From":"Old Series","Halloween":"Category 2: Halloween","Halloween Effect":"Category 2: Halloween","Median Hat Price":14.0},{"Name":"Dread Knot","Effect":"Amaranthine","Price":null,"Class":"Heavy","Item Type":"Cosmetic","Equip Region":"Regular","Grade":"No Grade","Unboxed From":"Old Series","Robo":false,"Generation":"Halloween 2014","Effect Community Rating":3.46875,"Crate Cosmetic":true,"Months Since Last Price Update":-1,"Effect Median Price":55.0,"Hat Median Price":14.0,"Hat Rating":null,"Effect Rating":null,"Median Effect Rating":2.5,"Median Hat Rating":-1.6,"GradeSize":"No Grade","Robo\/Misc\/Not":"Regular","Type of Crate Temp":false,"Type of Crate":"Category 2: Other Series","Crate Unboxed From":"Old Series","Halloween":"Category 2: Halloween","Halloween Effect":"Category 2: Halloween","Median Hat Price":14.0},{"Name":"Dread Knot","Effect":"Bonzo The All-Gnawing","Price":null,"Class":"Heavy","Item Type":"Cosmetic","Equip Region":"Regular","Grade":"No Grade","Unboxed From":"Old Series","Robo":false,"Generation":"Halloween 2014","Effect Community Rating":4.25,"Crate Cosmetic":true,"Months Since Last Price Update":-1,"Effect Median Price":138.5,"Hat Median Price":14.0,"Hat Rating":null,"Effect Rating":null,"Median Effect Rating":10.15,"Median Hat Rating":-1.6,"GradeSize":"No Grade","Robo\/Misc\/Not":"Regular","Type of Crate Temp":false,"Type of Crate":"Category 2: Other Series","Crate Unboxed From":"Old Series","Halloween":"Category 2: Halloween","Halloween Effect":"Category 2: Halloween","Median Hat Price":14.0},{"Name":"Dread Knot","Effect":"Ghastly Ghosts Jr","Price":null,"Class":"Heavy","Item Type":"Cosmetic","Equip Region":"Regular","Grade":"No Grade","Unboxed From":"Old Series","Robo":false,"Generation":"Halloween 2014","Effect Community Rating":2.8125,"Crate Cosmetic":true,"Months Since Last Price Update":-1,"Effect Median Price":52.5,"Hat Median Price":14.0,"Hat Rating":null,"Effect Rating":null,"Median Effect Rating":1.9,"Median Hat Rating":-1.6,"GradeSize":"No Grade","Robo\/Misc\/Not":"Regular","Type of Crate Temp":false,"Type of Crate":"Category 2: Other Series","Crate Unboxed From":"Old Series","Halloween":"Category 2: Halloween","Halloween Effect":"Category 2: Halloween","Median Hat Price":14.0},{"Name":"Dread Knot","Effect":"Haunted Phantasm Jr","Price":53.0,"Class":"Heavy","Item Type":"Cosmetic","Equip Region":"Regular","Grade":"No Grade","Unboxed From":"Old Series","Robo":false,"Generation":"Halloween 2014","Effect Community Rating":2.75,"Crate Cosmetic":true,"Months Since Last Price Update":43,"Effect Median Price":50.0,"Hat Median Price":14.0,"Hat Rating":0.3,"Effect Rating":3.9,"Median Effect Rating":1.6,"Median Hat Rating":-1.6,"GradeSize":"No Grade","Robo\/Misc\/Not":"Regular","Type of Crate Temp":false,"Type of Crate":"Category 2: Other Series","Crate Unboxed From":"Old Series","Halloween":"Category 2: Halloween","Halloween Effect":"Category 2: Halloween","Median Hat Price":14.0},{"Name":"Dread Knot","Effect":"Stare From Beyond","Price":null,"Class":"Heavy","Item Type":"Cosmetic","Equip Region":"Regular","Grade":"No Grade","Unboxed From":"Old Series","Robo":false,"Generation":"Halloween 2014","Effect Community Rating":3.40625,"Crate Cosmetic":true,"Months Since Last Price Update":-1,"Effect Median Price":60.0,"Hat Median Price":14.0,"Hat Rating":null,"Effect Rating":null,"Median Effect Rating":2.3375,"Median Hat Rating":-1.6,"GradeSize":"No Grade","Robo\/Misc\/Not":"Regular","Type of Crate Temp":false,"Type of Crate":"Category 2: Other Series","Crate Unboxed From":"Old Series","Halloween":"Category 2: Halloween","Halloween Effect":"Category 2: Halloween","Median Hat Price":14.0},{"Name":"Dread Knot","Effect":"The Ooze","Price":null,"Class":"Heavy","Item Type":"Cosmetic","Equip Region":"Regular","Grade":"No Grade","Unboxed From":"Old Series","Robo":false,"Generation":"Halloween 2014","Effect Community Rating":3.46875,"Crate Cosmetic":true,"Months Since Last Price Update":-1,"Effect Median Price":53.0,"Hat Median Price":14.0,"Hat Rating":null,"Effect Rating":null,"Median Effect Rating":2.25,"Median Hat Rating":-1.6,"GradeSize":"No Grade","Robo\/Misc\/Not":"Regular","Type of Crate Temp":false,"Type of Crate":"Category 2: Other Series","Crate Unboxed From":"Old Series","Halloween":"Category 2: Halloween","Halloween Effect":"Category 2: Halloween","Median Hat Price":14.0},{"Name":"Dread Knot","Effect":"Death by Disco","Price":null,"Class":"Heavy","Item Type":"Cosmetic","Equip Region":"Regular","Grade":"No Grade","Unboxed From":"Old Series","Robo":false,"Generation":"Halloween 2015","Effect Community Rating":3.09375,"Crate Cosmetic":true,"Months Since Last Price Update":-1,"Effect Median Price":59.5,"Hat Median Price":14.0,"Hat Rating":null,"Effect Rating":null,"Median Effect Rating":1.3125,"Median Hat Rating":-1.6,"GradeSize":"No Grade","Robo\/Misc\/Not":"Regular","Type of Crate Temp":false,"Type of Crate":"Category 2: Other Series","Crate Unboxed From":"Old Series","Halloween":"Category 2: Halloween","Halloween Effect":"Category 2: Halloween","Median Hat Price":14.0},{"Name":"Dread Knot","Effect":"It's a mystery to everyone","Price":null,"Class":"Heavy","Item Type":"Cosmetic","Equip Region":"Regular","Grade":"No Grade","Unboxed From":"Old Series","Robo":false,"Generation":"Halloween 2015","Effect Community Rating":2.75,"Crate Cosmetic":true,"Months Since Last Price Update":-1,"Effect Median Price":35.5,"Hat Median Price":14.0,"Hat Rating":null,"Effect Rating":null,"Median Effect Rating":-0.6625,"Median Hat Rating":-1.6,"GradeSize":"No Grade","Robo\/Misc\/Not":"Regular","Type of Crate Temp":false,"Type of Crate":"Category 2: Other Series","Crate Unboxed From":"Old Series","Halloween":"Category 2: Halloween","Halloween Effect":"Category 2: Halloween","Median Hat Price":14.0},{"Name":"Dread Knot","Effect":"It's a puzzle to me","Price":null,"Class":"Heavy","Item Type":"Cosmetic","Equip Region":"Regular","Grade":"No Grade","Unboxed From":"Old Series","Robo":false,"Generation":"Halloween 2015","Effect Community Rating":2.65625,"Crate Cosmetic":true,"Months Since Last Price Update":-1,"Effect Median Price":29.0,"Hat Median Price":14.0,"Hat Rating":null,"Effect Rating":null,"Median Effect Rating":-1.1125,"Median Hat Rating":-1.6,"GradeSize":"No Grade","Robo\/Misc\/Not":"Regular","Type of Crate Temp":false,"Type of Crate":"Category 2: Other Series","Crate Unboxed From":"Old Series","Halloween":"Category 2: Halloween","Halloween Effect":"Category 2: Halloween","Median Hat Price":14.0},{"Name":"Dread Knot","Effect":"Ether Trail","Price":null,"Class":"Heavy","Item Type":"Cosmetic","Equip Region":"Regular","Grade":"No Grade","Unboxed From":"Old Series","Robo":false,"Generation":"Halloween 2015","Effect Community Rating":3.03125,"Crate Cosmetic":true,"Months Since Last Price Update":-1,"Effect Median Price":31.25,"Hat Median Price":14.0,"Hat Rating":null,"Effect Rating":null,"Median Effect Rating":-0.3875,"Median Hat Rating":-1.6,"GradeSize":"No Grade","Robo\/Misc\/Not":"Regular","Type of Crate Temp":false,"Type of Crate":"Category 2: Other Series","Crate Unboxed From":"Old Series","Halloween":"Category 2: Halloween","Halloween Effect":"Category 2: Halloween","Median Hat Price":14.0},{"Name":"Dread Knot","Effect":"Nether Trail","Price":null,"Class":"Heavy","Item Type":"Cosmetic","Equip Region":"Regular","Grade":"No Grade","Unboxed From":"Old Series","Robo":false,"Generation":"Halloween 2015","Effect Community Rating":3.125,"Crate Cosmetic":true,"Months Since Last Price Update":-1,"Effect Median Price":43.75,"Hat Median Price":14.0,"Hat Rating":null,"Effect Rating":null,"Median Effect Rating":-0.0375,"Median Hat Rating":-1.6,"GradeSize":"No Grade","Robo\/Misc\/Not":"Regular","Type of Crate Temp":false,"Type of Crate":"Category 2: Other Series","Crate Unboxed From":"Old Series","Halloween":"Category 2: Halloween","Halloween Effect":"Category 2: Halloween","Median Hat Price":14.0},{"Name":"Dread Knot","Effect":"Ancient Eldritch","Price":null,"Class":"Heavy","Item Type":"Cosmetic","Equip Region":"Regular","Grade":"No Grade","Unboxed From":"Old Series","Robo":false,"Generation":"Halloween 2015","Effect Community Rating":2.875,"Crate Cosmetic":true,"Months Since Last Price Update":-1,"Effect Median Price":35.75,"Hat Median Price":14.0,"Hat Rating":null,"Effect Rating":null,"Median Effect Rating":-0.5,"Median Hat Rating":-1.6,"GradeSize":"No Grade","Robo\/Misc\/Not":"Regular","Type of Crate Temp":false,"Type of Crate":"Category 2: Other Series","Crate Unboxed From":"Old Series","Halloween":"Category 2: Halloween","Halloween Effect":"Category 2: Halloween","Median Hat Price":14.0},{"Name":"Dread Knot","Effect":"Eldritch Flame","Price":null,"Class":"Heavy","Item Type":"Cosmetic","Equip Region":"Regular","Grade":"No Grade","Unboxed From":"Old Series","Robo":false,"Generation":"Halloween 2015","Effect Community Rating":2.78125,"Crate Cosmetic":true,"Months Since Last Price Update":-1,"Effect Median Price":37.75,"Hat Median Price":14.0,"Hat Rating":null,"Effect Rating":null,"Median Effect Rating":-0.2,"Median Hat Rating":-1.6,"GradeSize":"No Grade","Robo\/Misc\/Not":"Regular","Type of Crate Temp":false,"Type of Crate":"Category 2: Other Series","Crate Unboxed From":"Old Series","Halloween":"Category 2: Halloween","Halloween Effect":"Category 2: Halloween","Median Hat Price":14.0},{"Name":"Dread Knot","Effect":"Neutron Star","Price":null,"Class":"Heavy","Item Type":"Cosmetic","Equip Region":"Regular","Grade":"No Grade","Unboxed From":"Old Series","Robo":false,"Generation":"Halloween 2016","Effect Community Rating":2.25,"Crate Cosmetic":true,"Months Since Last Price Update":-1,"Effect Median Price":27.25,"Hat Median Price":14.0,"Hat Rating":null,"Effect Rating":null,"Median Effect Rating":-0.375,"Median Hat Rating":-1.6,"GradeSize":"No Grade","Robo\/Misc\/Not":"Regular","Type of Crate Temp":false,"Type of Crate":"Category 2: Other Series","Crate Unboxed From":"Old Series","Halloween":"Category 2: Halloween","Halloween Effect":"Category 2: Halloween","Median Hat Price":14.0},{"Name":"Dread Knot","Effect":"Starstorm Slumber","Price":null,"Class":"Heavy","Item Type":"Cosmetic","Equip Region":"Regular","Grade":"No Grade","Unboxed From":"Old Series","Robo":false,"Generation":"Halloween 2016","Effect Community Rating":2.5,"Crate Cosmetic":true,"Months Since Last Price Update":-1,"Effect Median Price":32.5,"Hat Median Price":14.0,"Hat Rating":null,"Effect Rating":null,"Median Effect Rating":-0.15,"Median Hat Rating":-1.6,"GradeSize":"No Grade","Robo\/Misc\/Not":"Regular","Type of Crate Temp":false,"Type of Crate":"Category 2: Other Series","Crate Unboxed From":"Old Series","Halloween":"Category 2: Halloween","Halloween Effect":"Category 2: Halloween","Median Hat Price":14.0},{"Name":"Dread Knot","Effect":"Starstorm Insomnia","Price":48.0,"Class":"Heavy","Item Type":"Cosmetic","Equip Region":"Regular","Grade":"No Grade","Unboxed From":"Old Series","Robo":false,"Generation":"Halloween 2016","Effect Community Rating":2.4375,"Crate Cosmetic":true,"Months Since Last Price Update":27,"Effect Median Price":30.0,"Hat Median Price":14.0,"Hat Rating":1.8,"Effect Rating":3.4,"Median Effect Rating":-0.3,"Median Hat Rating":-1.6,"GradeSize":"No Grade","Robo\/Misc\/Not":"Regular","Type of Crate Temp":false,"Type of Crate":"Category 2: Other Series","Crate Unboxed From":"Old Series","Halloween":"Category 2: Halloween","Halloween Effect":"Category 2: Halloween","Median Hat Price":14.0},{"Name":"Dread Knot","Effect":"Tesla Coil","Price":56.0,"Class":"Heavy","Item Type":"Cosmetic","Equip Region":"Regular","Grade":"No Grade","Unboxed From":"Old Series","Robo":false,"Generation":"Halloween 2016","Effect Community Rating":2.875,"Crate Cosmetic":true,"Months Since Last Price Update":28,"Effect Median Price":38.25,"Hat Median Price":14.0,"Hat Rating":1.775,"Effect Rating":4.2,"Median Effect Rating":0.15,"Median Hat Rating":-1.6,"GradeSize":"No Grade","Robo\/Misc\/Not":"Regular","Type of Crate Temp":false,"Type of Crate":"Category 2: Other Series","Crate Unboxed From":"Old Series","Halloween":"Category 2: Halloween","Halloween Effect":"Category 2: Halloween","Median Hat Price":14.0},{"Name":"Dread Knot","Effect":"Brain Drain","Price":null,"Class":"Heavy","Item Type":"Cosmetic","Equip Region":"Regular","Grade":"No Grade","Unboxed From":"Old Series","Robo":false,"Generation":"Halloween 2018","Effect Community Rating":1.9375,"Crate Cosmetic":true,"Months Since Last Price Update":-1,"Effect Median Price":53.75,"Hat Median Price":14.0,"Hat Rating":null,"Effect Rating":null,"Median Effect Rating":2.7,"Median Hat Rating":-1.6,"GradeSize":"No Grade","Robo\/Misc\/Not":"Regular","Type of Crate Temp":false,"Type of Crate":"Category 2: Other Series","Crate Unboxed From":"Old Series","Halloween":"Category 2: Halloween","Halloween Effect":"Category 2: Halloween","Median Hat Price":14.0},{"Name":"Dread Knot","Effect":"Clairvoyance","Price":null,"Class":"Heavy","Item Type":"Cosmetic","Equip Region":"Regular","Grade":"No Grade","Unboxed From":"Old Series","Robo":false,"Generation":"Halloween 2018","Effect Community Rating":2.53125,"Crate Cosmetic":true,"Months Since Last Price Update":-1,"Effect Median Price":75.5,"Hat Median Price":14.0,"Hat Rating":null,"Effect Rating":null,"Median Effect Rating":1.275,"Median Hat Rating":-1.6,"GradeSize":"No Grade","Robo\/Misc\/Not":"Regular","Type of Crate Temp":false,"Type of Crate":"Category 2: Other Series","Crate Unboxed From":"Old Series","Halloween":"Category 2: Halloween","Halloween Effect":"Category 2: Halloween","Median Hat Price":14.0},{"Name":"Dread Knot","Effect":"Galactic Gateway","Price":null,"Class":"Heavy","Item Type":"Cosmetic","Equip Region":"Regular","Grade":"No Grade","Unboxed From":"Old Series","Robo":false,"Generation":"Halloween 2018","Effect Community Rating":4.40625,"Crate Cosmetic":true,"Months Since Last Price Update":-1,"Effect Median Price":90.0,"Hat Median Price":14.0,"Hat Rating":null,"Effect Rating":null,"Median Effect Rating":7.625,"Median Hat Rating":-1.6,"GradeSize":"No Grade","Robo\/Misc\/Not":"Regular","Type of Crate Temp":false,"Type of Crate":"Category 2: Other Series","Crate Unboxed From":"Old Series","Halloween":"Category 2: Halloween","Halloween Effect":"Category 2: Halloween","Median Hat Price":14.0},{"Name":"Dread Knot","Effect":"Head of Steam","Price":null,"Class":"Heavy","Item Type":"Cosmetic","Equip Region":"Regular","Grade":"No Grade","Unboxed From":"Old Series","Robo":false,"Generation":"Halloween 2018","Effect Community Rating":2.1875,"Crate Cosmetic":true,"Months Since Last Price Update":-1,"Effect Median Price":80.0,"Hat Median Price":14.0,"Hat Rating":null,"Effect Rating":null,"Median Effect Rating":1.725,"Median Hat Rating":-1.6,"GradeSize":"No Grade","Robo\/Misc\/Not":"Regular","Type of Crate Temp":false,"Type of Crate":"Category 2: Other Series","Crate Unboxed From":"Old Series","Halloween":"Category 2: Halloween","Halloween Effect":"Category 2: Halloween","Median Hat Price":14.0},{"Name":"Dread Knot","Effect":"Omniscient Orb","Price":null,"Class":"Heavy","Item Type":"Cosmetic","Equip Region":"Regular","Grade":"No Grade","Unboxed From":"Old Series","Robo":false,"Generation":"Halloween 2018","Effect Community Rating":2.15625,"Crate Cosmetic":true,"Months Since Last Price Update":-1,"Effect Median Price":39.0,"Hat Median Price":14.0,"Hat Rating":null,"Effect Rating":null,"Median Effect Rating":1.0,"Median Hat Rating":-1.6,"GradeSize":"No Grade","Robo\/Misc\/Not":"Regular","Type of Crate Temp":false,"Type of Crate":"Category 2: Other Series","Crate Unboxed From":"Old Series","Halloween":"Category 2: Halloween","Halloween Effect":"Category 2: Halloween","Median Hat Price":14.0},{"Name":"Dread Knot","Effect":"Open Mind","Price":null,"Class":"Heavy","Item Type":"Cosmetic","Equip Region":"Regular","Grade":"No Grade","Unboxed From":"Old Series","Robo":false,"Generation":"Halloween 2018","Effect Community Rating":2.0625,"Crate Cosmetic":true,"Months Since Last Price Update":-1,"Effect Median Price":30.5,"Hat Median Price":14.0,"Hat Rating":null,"Effect Rating":null,"Median Effect Rating":-0.1875,"Median Hat Rating":-1.6,"GradeSize":"No Grade","Robo\/Misc\/Not":"Regular","Type of Crate Temp":false,"Type of Crate":"Category 2: Other Series","Crate Unboxed From":"Old Series","Halloween":"Category 2: Halloween","Halloween Effect":"Category 2: Halloween","Median Hat Price":14.0},{"Name":"Dread Knot","Effect":"Ring of Fire","Price":null,"Class":"Heavy","Item Type":"Cosmetic","Equip Region":"Regular","Grade":"No Grade","Unboxed From":"Old Series","Robo":false,"Generation":"Halloween 2018","Effect Community Rating":2.59375,"Crate Cosmetic":true,"Months Since Last Price Update":-1,"Effect Median Price":105.0,"Hat Median Price":14.0,"Hat Rating":null,"Effect Rating":null,"Median Effect Rating":6.65,"Median Hat Rating":-1.6,"GradeSize":"No Grade","Robo\/Misc\/Not":"Regular","Type of Crate Temp":false,"Type of Crate":"Category 2: Other Series","Crate Unboxed From":"Old Series","Halloween":"Category 2: Halloween","Halloween Effect":"Category 2: Halloween","Median Hat Price":14.0},{"Name":"Dread Knot","Effect":"The Dark Doorway","Price":null,"Class":"Heavy","Item Type":"Cosmetic","Equip Region":"Regular","Grade":"No Grade","Unboxed From":"Old Series","Robo":false,"Generation":"Halloween 2018","Effect Community Rating":4.3125,"Crate Cosmetic":true,"Months Since Last Price Update":-1,"Effect Median Price":84.0,"Hat Median Price":14.0,"Hat Rating":null,"Effect Rating":null,"Median Effect Rating":5.85,"Median Hat Rating":-1.6,"GradeSize":"No Grade","Robo\/Misc\/Not":"Regular","Type of Crate Temp":false,"Type of Crate":"Category 2: Other Series","Crate Unboxed From":"Old Series","Halloween":"Category 2: Halloween","Halloween Effect":"Category 2: Halloween","Median Hat Price":14.0},{"Name":"Dread Knot","Effect":"The Eldritch Opening","Price":null,"Class":"Heavy","Item Type":"Cosmetic","Equip Region":"Regular","Grade":"No Grade","Unboxed From":"Old Series","Robo":false,"Generation":"Halloween 2018","Effect Community Rating":4.28125,"Crate Cosmetic":true,"Months Since Last Price Update":-1,"Effect Median Price":102.25,"Hat Median Price":14.0,"Hat Rating":null,"Effect Rating":null,"Median Effect Rating":8.0125,"Median Hat Rating":-1.6,"GradeSize":"No Grade","Robo\/Misc\/Not":"Regular","Type of Crate Temp":false,"Type of Crate":"Category 2: Other Series","Crate Unboxed From":"Old Series","Halloween":"Category 2: Halloween","Halloween Effect":"Category 2: Halloween","Median Hat Price":14.0},{"Name":"Dread Knot","Effect":"Vicious Circle","Price":null,"Class":"Heavy","Item Type":"Cosmetic","Equip Region":"Regular","Grade":"No Grade","Unboxed From":"Old Series","Robo":false,"Generation":"Halloween 2018","Effect Community Rating":2.40625,"Crate Cosmetic":true,"Months Since Last Price Update":-1,"Effect Median Price":23.5,"Hat Median Price":14.0,"Hat Rating":null,"Effect Rating":null,"Median Effect Rating":0.3,"Median Hat Rating":-1.6,"GradeSize":"No Grade","Robo\/Misc\/Not":"Regular","Type of Crate Temp":false,"Type of Crate":"Category 2: Other Series","Crate Unboxed From":"Old Series","Halloween":"Category 2: Halloween","Halloween Effect":"Category 2: Halloween","Median Hat Price":14.0},{"Name":"Dread Knot","Effect":"White Lightning","Price":null,"Class":"Heavy","Item Type":"Cosmetic","Equip Region":"Regular","Grade":"No Grade","Unboxed From":"Old Series","Robo":false,"Generation":"Halloween 2018","Effect Community Rating":2.71875,"Crate Cosmetic":true,"Months Since Last Price Update":-1,"Effect Median Price":61.5,"Hat Median Price":14.0,"Hat Rating":null,"Effect Rating":null,"Median Effect Rating":1.55,"Median Hat Rating":-1.6,"GradeSize":"No Grade","Robo\/Misc\/Not":"Regular","Type of Crate Temp":false,"Type of Crate":"Category 2: Other Series","Crate Unboxed From":"Old Series","Halloween":"Category 2: Halloween","Halloween Effect":"Category 2: Halloween","Median Hat Price":14.0},{"Name":"Dread Knot","Effect":"Anti-Freeze","Price":null,"Class":"Heavy","Item Type":"Cosmetic","Equip Region":"Regular","Grade":"No Grade","Unboxed From":"Old Series","Robo":false,"Generation":"Robotic Boogaloo","Effect Community Rating":3.40625,"Crate Cosmetic":true,"Months Since Last Price Update":-1,"Effect Median Price":77.0,"Hat Median Price":14.0,"Hat Rating":null,"Effect Rating":null,"Median Effect Rating":4.5375,"Median Hat Rating":-1.6,"GradeSize":"No Grade","Robo\/Misc\/Not":"Regular","Type of Crate Temp":false,"Type of Crate":"Category 2: Other Series","Crate Unboxed From":"Robotic Boogaloo","Halloween":"Category 1: Regular","Halloween Effect":"Category 1: Regular","Median Hat Price":14.0},{"Name":"Dread Knot","Effect":"Electrostatic","Price":16.0,"Class":"Heavy","Item Type":"Cosmetic","Equip Region":"Regular","Grade":"No Grade","Unboxed From":"Old Series","Robo":false,"Generation":"Robotic Boogaloo","Effect Community Rating":1.875,"Crate Cosmetic":true,"Months Since Last Price Update":10,"Effect Median Price":25.0,"Hat Median Price":14.0,"Hat Rating":-0.9,"Effect Rating":0.2,"Median Effect Rating":-0.4,"Median Hat Rating":-1.6,"GradeSize":"No Grade","Robo\/Misc\/Not":"Regular","Type of Crate Temp":false,"Type of Crate":"Category 2: Other Series","Crate Unboxed From":"Robotic Boogaloo","Halloween":"Category 1: Regular","Halloween Effect":"Category 1: Regular","Median Hat Price":14.0},{"Name":"Dread Knot","Effect":"Green Black Hole","Price":27.0,"Class":"Heavy","Item Type":"Cosmetic","Equip Region":"Regular","Grade":"No Grade","Unboxed From":"Old Series","Robo":false,"Generation":"Robotic Boogaloo","Effect Community Rating":3.8125,"Crate Cosmetic":true,"Months Since Last Price Update":1,"Effect Median Price":52.0,"Hat Median Price":14.0,"Hat Rating":-2.5,"Effect Rating":1.3,"Median Effect Rating":2.15,"Median Hat Rating":-1.6,"GradeSize":"No Grade","Robo\/Misc\/Not":"Regular","Type of Crate Temp":false,"Type of Crate":"Category 2: Other Series","Crate Unboxed From":"Robotic Boogaloo","Halloween":"Category 1: Regular","Halloween Effect":"Category 1: Regular","Median Hat Price":14.0},{"Name":"Dread Knot","Effect":"Memory Leak","Price":11.0,"Class":"Heavy","Item Type":"Cosmetic","Equip Region":"Regular","Grade":"No Grade","Unboxed From":"Old Series","Robo":false,"Generation":"Robotic Boogaloo","Effect Community Rating":1.03125,"Crate Cosmetic":true,"Months Since Last Price Update":3,"Effect Median Price":22.0,"Hat Median Price":14.0,"Hat Rating":-1.1,"Effect Rating":-0.3,"Median Effect Rating":-0.8,"Median Hat Rating":-1.6,"GradeSize":"No Grade","Robo\/Misc\/Not":"Regular","Type of Crate Temp":false,"Type of Crate":"Category 2: Other Series","Crate Unboxed From":"Robotic Boogaloo","Halloween":"Category 1: Regular","Halloween Effect":"Category 1: Regular","Median Hat Price":14.0},{"Name":"Dread Knot","Effect":"Overclocked","Price":null,"Class":"Heavy","Item Type":"Cosmetic","Equip Region":"Regular","Grade":"No Grade","Unboxed From":"Old Series","Robo":false,"Generation":"Robotic Boogaloo","Effect Community Rating":1.09375,"Crate Cosmetic":true,"Months Since Last Price Update":-1,"Effect Median Price":20.0,"Hat Median Price":14.0,"Hat Rating":null,"Effect Rating":null,"Median Effect Rating":-1.1,"Median Hat Rating":-1.6,"GradeSize":"No Grade","Robo\/Misc\/Not":"Regular","Type of Crate Temp":false,"Type of Crate":"Category 2: Other Series","Crate Unboxed From":"Robotic Boogaloo","Halloween":"Category 1: Regular","Halloween Effect":"Category 1: Regular","Median Hat Price":14.0},{"Name":"Dread Knot","Effect":"Phosphorous","Price":23.5,"Class":"Heavy","Item Type":"Cosmetic","Equip Region":"Regular","Grade":"No Grade","Unboxed From":"Old Series","Robo":false,"Generation":"Robotic Boogaloo","Effect Community Rating":2.46875,"Crate Cosmetic":true,"Months Since Last Price Update":13,"Effect Median Price":42.0,"Hat Median Price":14.0,"Hat Rating":-1.85,"Effect Rating":0.95,"Median Effect Rating":0.8375,"Median Hat Rating":-1.6,"GradeSize":"No Grade","Robo\/Misc\/Not":"Regular","Type of Crate Temp":false,"Type of Crate":"Category 2: Other Series","Crate Unboxed From":"Robotic Boogaloo","Halloween":"Category 1: Regular","Halloween Effect":"Category 1: Regular","Median Hat Price":14.0},{"Name":"Dread Knot","Effect":"Power Surge","Price":16.0,"Class":"Heavy","Item Type":"Cosmetic","Equip Region":"Regular","Grade":"No Grade","Unboxed From":"Old Series","Robo":false,"Generation":"Robotic Boogaloo","Effect Community Rating":1.96875,"Crate Cosmetic":true,"Months Since Last Price Update":35,"Effect Median Price":29.0,"Hat Median Price":14.0,"Hat Rating":-1.3,"Effect Rating":0.2,"Median Effect Rating":-0.2,"Median Hat Rating":-1.6,"GradeSize":"No Grade","Robo\/Misc\/Not":"Regular","Type of Crate Temp":false,"Type of Crate":"Category 2: Other Series","Crate Unboxed From":"Robotic Boogaloo","Halloween":"Category 1: Regular","Halloween Effect":"Category 1: Regular","Median Hat Price":14.0},{"Name":"Dread Knot","Effect":"Roboactive","Price":null,"Class":"Heavy","Item Type":"Cosmetic","Equip Region":"Regular","Grade":"No Grade","Unboxed From":"Old Series","Robo":false,"Generation":"Robotic Boogaloo","Effect Community Rating":3.6129032258,"Crate Cosmetic":true,"Months Since Last Price Update":-1,"Effect Median Price":70.0,"Hat Median Price":14.0,"Hat Rating":null,"Effect Rating":null,"Median Effect Rating":4.2,"Median Hat Rating":-1.6,"GradeSize":"No Grade","Robo\/Misc\/Not":"Regular","Type of Crate Temp":false,"Type of Crate":"Category 2: Other Series","Crate Unboxed From":"Robotic Boogaloo","Halloween":"Category 1: Regular","Halloween Effect":"Category 1: Regular","Median Hat Price":14.0},{"Name":"Dread Knot","Effect":"Sulphurous","Price":24.0,"Class":"Heavy","Item Type":"Cosmetic","Equip Region":"Regular","Grade":"No Grade","Unboxed From":"Old Series","Robo":false,"Generation":"Robotic Boogaloo","Effect Community Rating":2.53125,"Crate Cosmetic":true,"Months Since Last Price Update":43,"Effect Median Price":42.0,"Hat Median Price":14.0,"Hat Rating":-1.8,"Effect Rating":1.0,"Median Effect Rating":1.05,"Median Hat Rating":-1.6,"GradeSize":"No Grade","Robo\/Misc\/Not":"Regular","Type of Crate Temp":false,"Type of Crate":"Category 2: Other Series","Crate Unboxed From":"Robotic Boogaloo","Halloween":"Category 1: Regular","Halloween Effect":"Category 1: Regular","Median Hat Price":14.0},{"Name":"Dread Knot","Effect":"Time Warp","Price":30.0,"Class":"Heavy","Item Type":"Cosmetic","Equip Region":"Regular","Grade":"No Grade","Unboxed From":"Old Series","Robo":false,"Generation":"Robotic Boogaloo","Effect Community Rating":4.0,"Crate Cosmetic":true,"Months Since Last Price Update":11,"Effect Median Price":57.25,"Hat Median Price":14.0,"Hat Rating":-2.725,"Effect Rating":1.6,"Median Effect Rating":2.2,"Median Hat Rating":-1.6,"GradeSize":"No Grade","Robo\/Misc\/Not":"Regular","Type of Crate Temp":false,"Type of Crate":"Category 2: Other Series","Crate Unboxed From":"Robotic Boogaloo","Halloween":"Category 1: Regular","Halloween Effect":"Category 1: Regular","Median Hat Price":14.0},{"Name":"Dread Knot","Effect":"Death at Dusk","Price":32.5,"Class":"Heavy","Item Type":"Cosmetic","Equip Region":"Regular","Grade":"No Grade","Unboxed From":"Old Series","Robo":false,"Generation":"End of the Line","Effect Community Rating":4.28125,"Crate Cosmetic":true,"Months Since Last Price Update":41,"Effect Median Price":50.0,"Hat Median Price":14.0,"Hat Rating":-1.75,"Effect Rating":1.85,"Median Effect Rating":1.95,"Median Hat Rating":-1.6,"GradeSize":"No Grade","Robo\/Misc\/Not":"Regular","Type of Crate Temp":false,"Type of Crate":"Category 2: Other Series","Crate Unboxed From":"End of the Line","Halloween":"Category 1: Regular","Halloween Effect":"Category 1: Regular","Median Hat Price":14.0},{"Name":"Dread Knot","Effect":"Frostbite","Price":31.5,"Class":"Heavy","Item Type":"Cosmetic","Equip Region":"Regular","Grade":"No Grade","Unboxed From":"Old Series","Robo":false,"Generation":"End of the Line","Effect Community Rating":4.4375,"Crate Cosmetic":true,"Months Since Last Price Update":4,"Effect Median Price":60.0,"Hat Median Price":14.0,"Hat Rating":-2.85,"Effect Rating":1.75,"Median Effect Rating":2.7,"Median Hat Rating":-1.6,"GradeSize":"No Grade","Robo\/Misc\/Not":"Regular","Type of Crate Temp":false,"Type of Crate":"Category 2: Other Series","Crate Unboxed From":"End of the Line","Halloween":"Category 1: Regular","Halloween Effect":"Category 1: Regular","Median Hat Price":14.0},{"Name":"Dread Knot","Effect":"Molten Mallard","Price":19.0,"Class":"Heavy","Item Type":"Cosmetic","Equip Region":"Regular","Grade":"No Grade","Unboxed From":"Old Series","Robo":false,"Generation":"End of the Line","Effect Community Rating":2.375,"Crate Cosmetic":true,"Months Since Last Price Update":42,"Effect Median Price":35.0,"Hat Median Price":14.0,"Hat Rating":-1.6,"Effect Rating":0.5,"Median Effect Rating":0.1,"Median Hat Rating":-1.6,"GradeSize":"No Grade","Robo\/Misc\/Not":"Regular","Type of Crate Temp":false,"Type of Crate":"Category 2: Other Series","Crate Unboxed From":"End of the Line","Halloween":"Category 1: Regular","Halloween Effect":"Category 1: Regular","Median Hat Price":14.0},{"Name":"Dread Knot","Effect":"Morning Glory","Price":null,"Class":"Heavy","Item Type":"Cosmetic","Equip Region":"Regular","Grade":"No Grade","Unboxed From":"Old Series","Robo":false,"Generation":"End of the Line","Effect Community Rating":4.15625,"Crate Cosmetic":true,"Months Since Last Price Update":-1,"Effect Median Price":50.75,"Hat Median Price":14.0,"Hat Rating":null,"Effect Rating":null,"Median Effect Rating":1.9375,"Median Hat Rating":-1.6,"GradeSize":"No Grade","Robo\/Misc\/Not":"Regular","Type of Crate Temp":false,"Type of Crate":"Category 2: Other Series","Crate Unboxed From":"End of the Line","Halloween":"Category 1: Regular","Halloween Effect":"Category 1: Regular","Median Hat Price":14.0},{"Name":"Dread Knot","Effect":"Abduction","Price":null,"Class":"Heavy","Item Type":"Cosmetic","Equip Region":"Regular","Grade":"No Grade","Unboxed From":"Old Series","Robo":false,"Generation":"Invasion","Effect Community Rating":2.9375,"Crate Cosmetic":true,"Months Since Last Price Update":-1,"Effect Median Price":153.75,"Hat Median Price":14.0,"Hat Rating":null,"Effect Rating":null,"Median Effect Rating":7.375,"Median Hat Rating":-1.6,"GradeSize":"No Grade","Robo\/Misc\/Not":"Regular","Type of Crate Temp":false,"Type of Crate":"Category 2: Other Series","Crate Unboxed From":"Old Series","Halloween":"Category 1: Regular","Halloween Effect":"Category 1: Regular","Median Hat Price":14.0},{"Name":"Dread Knot","Effect":"Atomic","Price":null,"Class":"Heavy","Item Type":"Cosmetic","Equip Region":"Regular","Grade":"No Grade","Unboxed From":"Old Series","Robo":false,"Generation":"Invasion","Effect Community Rating":2.3125,"Crate Cosmetic":true,"Months Since Last Price Update":-1,"Effect Median Price":89.25,"Hat Median Price":14.0,"Hat Rating":null,"Effect Rating":null,"Median Effect Rating":-0.25,"Median Hat Rating":-1.6,"GradeSize":"No Grade","Robo\/Misc\/Not":"Regular","Type of Crate Temp":false,"Type of Crate":"Category 2: Other Series","Crate Unboxed From":"Old Series","Halloween":"Category 1: Regular","Halloween Effect":"Category 1: Regular","Median Hat Price":14.0},{"Name":"Dread Knot","Effect":"Subatomic","Price":null,"Class":"Heavy","Item Type":"Cosmetic","Equip Region":"Regular","Grade":"No Grade","Unboxed From":"Old Series","Robo":false,"Generation":"Invasion","Effect Community Rating":2.28125,"Crate Cosmetic":true,"Months Since Last Price Update":-1,"Effect Median Price":64.5,"Hat Median Price":14.0,"Hat Rating":null,"Effect Rating":null,"Median Effect Rating":0.575,"Median Hat Rating":-1.6,"GradeSize":"No Grade","Robo\/Misc\/Not":"Regular","Type of Crate Temp":false,"Type of Crate":"Category 2: Other Series","Crate Unboxed From":"Old Series","Halloween":"Category 1: Regular","Halloween Effect":"Category 1: Regular","Median Hat Price":14.0},{"Name":"Dread Knot","Effect":"Electric Hat Protector","Price":null,"Class":"Heavy","Item Type":"Cosmetic","Equip Region":"Regular","Grade":"No Grade","Unboxed From":"Old Series","Robo":false,"Generation":"Invasion","Effect Community Rating":2.15625,"Crate Cosmetic":true,"Months Since Last Price Update":-1,"Effect Median Price":45.75,"Hat Median Price":14.0,"Hat Rating":null,"Effect Rating":null,"Median Effect Rating":-1.6,"Median Hat Rating":-1.6,"GradeSize":"No Grade","Robo\/Misc\/Not":"Regular","Type of Crate Temp":false,"Type of Crate":"Category 2: Other Series","Crate Unboxed From":"Old Series","Halloween":"Category 1: Regular","Halloween Effect":"Category 1: Regular","Median Hat Price":14.0},{"Name":"Dread Knot","Effect":"Magnetic Hat Protector","Price":null,"Class":"Heavy","Item Type":"Cosmetic","Equip Region":"Regular","Grade":"No Grade","Unboxed From":"Old Series","Robo":false,"Generation":"Invasion","Effect Community Rating":2.15625,"Crate Cosmetic":true,"Months Since Last Price Update":-1,"Effect Median Price":20.5,"Hat Median Price":14.0,"Hat Rating":null,"Effect Rating":null,"Median Effect Rating":-0.9,"Median Hat Rating":-1.6,"GradeSize":"No Grade","Robo\/Misc\/Not":"Regular","Type of Crate Temp":false,"Type of Crate":"Category 2: Other Series","Crate Unboxed From":"Old Series","Halloween":"Category 1: Regular","Halloween Effect":"Category 1: Regular","Median Hat Price":14.0},{"Name":"Dread Knot","Effect":"Voltaic Hat Protector","Price":null,"Class":"Heavy","Item Type":"Cosmetic","Equip Region":"Regular","Grade":"No Grade","Unboxed From":"Old Series","Robo":false,"Generation":"Invasion","Effect Community Rating":2.09375,"Crate Cosmetic":true,"Months Since Last Price Update":-1,"Effect Median Price":52.5,"Hat Median Price":14.0,"Hat Rating":null,"Effect Rating":null,"Median Effect Rating":-1.175,"Median Hat Rating":-1.6,"GradeSize":"No Grade","Robo\/Misc\/Not":"Regular","Type of Crate Temp":false,"Type of Crate":"Category 2: Other Series","Crate Unboxed From":"Old Series","Halloween":"Category 1: Regular","Halloween Effect":"Category 1: Regular","Median Hat Price":14.0},{"Name":"Dread Knot","Effect":"Galactic Codex","Price":null,"Class":"Heavy","Item Type":"Cosmetic","Equip Region":"Regular","Grade":"No Grade","Unboxed From":"Old Series","Robo":false,"Generation":"Invasion","Effect Community Rating":1.4375,"Crate Cosmetic":true,"Months Since Last Price Update":-1,"Effect Median Price":36.75,"Hat Median Price":14.0,"Hat Rating":null,"Effect Rating":null,"Median Effect Rating":-1.1,"Median Hat Rating":-1.6,"GradeSize":"No Grade","Robo\/Misc\/Not":"Regular","Type of Crate Temp":false,"Type of Crate":"Category 2: Other Series","Crate Unboxed From":"Old Series","Halloween":"Category 1: Regular","Halloween Effect":"Category 1: Regular","Median Hat Price":14.0},{"Name":"Dread Knot","Effect":"Ancient Codex","Price":null,"Class":"Heavy","Item Type":"Cosmetic","Equip Region":"Regular","Grade":"No Grade","Unboxed From":"Old Series","Robo":false,"Generation":"Invasion","Effect Community Rating":1.46875,"Crate Cosmetic":true,"Months Since Last Price Update":-1,"Effect Median Price":19.5,"Hat Median Price":14.0,"Hat Rating":null,"Effect Rating":null,"Median Effect Rating":-1.25,"Median Hat Rating":-1.6,"GradeSize":"No Grade","Robo\/Misc\/Not":"Regular","Type of Crate Temp":false,"Type of Crate":"Category 2: Other Series","Crate Unboxed From":"Old Series","Halloween":"Category 1: Regular","Halloween Effect":"Category 1: Regular","Median Hat Price":14.0},{"Name":"Dread Knot","Effect":"Nebula","Price":null,"Class":"Heavy","Item Type":"Cosmetic","Equip Region":"Regular","Grade":"No Grade","Unboxed From":"Old Series","Robo":false,"Generation":"Invasion","Effect Community Rating":4.875,"Crate Cosmetic":true,"Months Since Last Price Update":-1,"Effect Median Price":180.0,"Hat Median Price":14.0,"Hat Rating":null,"Effect Rating":null,"Median Effect Rating":14.5,"Median Hat Rating":-1.6,"GradeSize":"No Grade","Robo\/Misc\/Not":"Regular","Type of Crate Temp":false,"Type of Crate":"Category 2: Other Series","Crate Unboxed From":"Old Series","Halloween":"Category 1: Regular","Halloween Effect":"Category 1: Regular","Median Hat Price":14.0},{"Name":"Shred Alert","Effect":"Ghastly Ghosts","Price":null,"Class":"All classes","Item Type":"Taunt","Equip Region":"Regular","Grade":"No Grade","Unboxed From":"Unusualifier","Robo":false,"Generation":"Halloween 2014","Effect Community Rating":2.90625,"Crate Cosmetic":false,"Months Since Last Price Update":-1,"Effect Median Price":32.0,"Hat Median Price":11.0,"Hat Rating":null,"Effect Rating":null,"Median Effect Rating":2.05,"Median Hat Rating":0.1,"GradeSize":"No Grade","Robo\/Misc\/Not":"Regular","Type of Crate Temp":false,"Type of Crate":"Category 2: Other Series","Crate Unboxed From":"Unusualifier","Halloween":"Category 2: Halloween","Halloween Effect":"Category 2: Halloween","Median Hat Price":11.0},{"Name":"Shred Alert","Effect":"Haunted Phantasm","Price":null,"Class":"All classes","Item Type":"Taunt","Equip Region":"Regular","Grade":"No Grade","Unboxed From":"Unusualifier","Robo":false,"Generation":"Halloween 2014","Effect Community Rating":2.96875,"Crate Cosmetic":false,"Months Since Last Price Update":-1,"Effect Median Price":24.0,"Hat Median Price":11.0,"Hat Rating":null,"Effect Rating":null,"Median Effect Rating":1.425,"Median Hat Rating":0.1,"GradeSize":"No Grade","Robo\/Misc\/Not":"Regular","Type of Crate Temp":false,"Type of Crate":"Category 2: Other Series","Crate Unboxed From":"Unusualifier","Halloween":"Category 2: Halloween","Halloween Effect":"Category 2: Halloween","Median Hat Price":11.0},{"Name":"Shred Alert","Effect":"Spectral Swirl","Price":26.0,"Class":"All classes","Item Type":"Taunt","Equip Region":"Regular","Grade":"No Grade","Unboxed From":"Unusualifier","Robo":false,"Generation":"Halloween 2016","Effect Community Rating":2.875,"Crate Cosmetic":false,"Months Since Last Price Update":17,"Effect Median Price":25.0,"Hat Median Price":11.0,"Hat Rating":0.1,"Effect Rating":1.5,"Median Effect Rating":1.3,"Median Hat Rating":0.1,"GradeSize":"No Grade","Robo\/Misc\/Not":"Regular","Type of Crate Temp":false,"Type of Crate":"Category 2: Other Series","Crate Unboxed From":"Unusualifier","Halloween":"Category 2: Halloween","Halloween Effect":"Category 2: Halloween","Median Hat Price":11.0},{"Name":"Shred Alert","Effect":"Hellish Inferno","Price":55.0,"Class":"All classes","Item Type":"Taunt","Equip Region":"Regular","Grade":"No Grade","Unboxed From":"Unusualifier","Robo":false,"Generation":"Halloween 2016","Effect Community Rating":2.875,"Crate Cosmetic":false,"Months Since Last Price Update":22,"Effect Median Price":18.25,"Hat Median Price":11.0,"Hat Rating":3.675,"Effect Rating":4.4,"Median Effect Rating":0.775,"Median Hat Rating":0.1,"GradeSize":"No Grade","Robo\/Misc\/Not":"Regular","Type of Crate Temp":false,"Type of Crate":"Category 2: Other Series","Crate Unboxed From":"Unusualifier","Halloween":"Category 2: Halloween","Halloween Effect":"Category 2: Halloween","Median Hat Price":11.0},{"Name":"Shred Alert","Effect":"Infernal Smoke","Price":23.0,"Class":"All classes","Item Type":"Taunt","Equip Region":"Regular","Grade":"No Grade","Unboxed From":"Unusualifier","Robo":false,"Generation":"Halloween 2016","Effect Community Rating":3.0625,"Crate Cosmetic":false,"Months Since Last Price Update":4,"Effect Median Price":23.25,"Hat Median Price":11.0,"Hat Rating":-0.025,"Effect Rating":1.2,"Median Effect Rating":1.08125,"Median Hat Rating":0.1,"GradeSize":"No Grade","Robo\/Misc\/Not":"Regular","Type of Crate Temp":false,"Type of Crate":"Category 2: Other Series","Crate Unboxed From":"Unusualifier","Halloween":"Category 2: Halloween","Halloween Effect":"Category 2: Halloween","Median Hat Price":11.0},{"Name":"Shred Alert","Effect":"Infernal Flames","Price":21.0,"Class":"All classes","Item Type":"Taunt","Equip Region":"Regular","Grade":"No Grade","Unboxed From":"Unusualifier","Robo":false,"Generation":"Halloween 2016","Effect Community Rating":3.15625,"Crate Cosmetic":false,"Months Since Last Price Update":7,"Effect Median Price":21.0,"Hat Median Price":11.0,"Hat Rating":0.0,"Effect Rating":1.0,"Median Effect Rating":0.9875,"Median Hat Rating":0.1,"GradeSize":"No Grade","Robo\/Misc\/Not":"Regular","Type of Crate Temp":false,"Type of Crate":"Category 2: Other Series","Crate Unboxed From":"Unusualifier","Halloween":"Category 2: Halloween","Halloween Effect":"Category 2: Halloween","Median Hat Price":11.0},{"Name":"Shred Alert","Effect":"Acidic Bubbles of Envy","Price":null,"Class":"All classes","Item Type":"Taunt","Equip Region":"Regular","Grade":"No Grade","Unboxed From":"Unusualifier","Robo":false,"Generation":"Halloween 2018","Effect Community Rating":1.78125,"Crate Cosmetic":false,"Months Since Last Price Update":-1,"Effect Median Price":8.0,"Hat Median Price":11.0,"Hat Rating":null,"Effect Rating":null,"Median Effect Rating":0.0,"Median Hat Rating":0.1,"GradeSize":"No Grade","Robo\/Misc\/Not":"Regular","Type of Crate Temp":false,"Type of Crate":"Category 2: Other Series","Crate Unboxed From":"Unusualifier","Halloween":"Category 2: Halloween","Halloween Effect":"Category 2: Halloween","Median Hat Price":11.0},{"Name":"Shred Alert","Effect":"Flammable Bubbles of Attraction","Price":null,"Class":"All classes","Item Type":"Taunt","Equip Region":"Regular","Grade":"No Grade","Unboxed From":"Unusualifier","Robo":false,"Generation":"Halloween 2018","Effect Community Rating":1.875,"Crate Cosmetic":false,"Months Since Last Price Update":-1,"Effect Median Price":9.0,"Hat Median Price":11.0,"Hat Rating":null,"Effect Rating":null,"Median Effect Rating":0.0125,"Median Hat Rating":0.1,"GradeSize":"No Grade","Robo\/Misc\/Not":"Regular","Type of Crate Temp":false,"Type of Crate":"Category 2: Other Series","Crate Unboxed From":"Unusualifier","Halloween":"Category 2: Halloween","Halloween Effect":"Category 2: Halloween","Median Hat Price":11.0},{"Name":"Shred Alert","Effect":"Poisonous Bubbles of Regret","Price":null,"Class":"All classes","Item Type":"Taunt","Equip Region":"Regular","Grade":"No Grade","Unboxed From":"Unusualifier","Robo":false,"Generation":"Halloween 2018","Effect Community Rating":1.875,"Crate Cosmetic":false,"Months Since Last Price Update":-1,"Effect Median Price":16.5,"Hat Median Price":11.0,"Hat Rating":null,"Effect Rating":null,"Median Effect Rating":-0.1125,"Median Hat Rating":0.1,"GradeSize":"No Grade","Robo\/Misc\/Not":"Regular","Type of Crate Temp":false,"Type of Crate":"Category 2: Other Series","Crate Unboxed From":"Unusualifier","Halloween":"Category 2: Halloween","Halloween Effect":"Category 2: Halloween","Median Hat Price":11.0},{"Name":"Shred Alert","Effect":"Roaring Rockets","Price":7.5,"Class":"All classes","Item Type":"Taunt","Equip Region":"Regular","Grade":"No Grade","Unboxed From":"Unusualifier","Robo":false,"Generation":"Halloween 2018","Effect Community Rating":1.8125,"Crate Cosmetic":false,"Months Since Last Price Update":2,"Effect Median Price":9.0,"Hat Median Price":11.0,"Hat Rating":-0.15,"Effect Rating":-0.35,"Median Effect Rating":-0.51875,"Median Hat Rating":0.1,"GradeSize":"No Grade","Robo\/Misc\/Not":"Regular","Type of Crate Temp":false,"Type of Crate":"Category 2: Other Series","Crate Unboxed From":"Unusualifier","Halloween":"Category 2: Halloween","Halloween Effect":"Category 2: Halloween","Median Hat Price":11.0},{"Name":"Shred Alert","Effect":"Spooky Night","Price":null,"Class":"All classes","Item Type":"Taunt","Equip Region":"Regular","Grade":"No Grade","Unboxed From":"Unusualifier","Robo":false,"Generation":"Halloween 2018","Effect Community Rating":3.0625,"Crate Cosmetic":false,"Months Since Last Price Update":-1,"Effect Median Price":26.5,"Hat Median Price":11.0,"Hat Rating":null,"Effect Rating":null,"Median Effect Rating":0.9625,"Median Hat Rating":0.1,"GradeSize":"No Grade","Robo\/Misc\/Not":"Regular","Type of Crate Temp":false,"Type of Crate":"Category 2: Other Series","Crate Unboxed From":"Unusualifier","Halloween":"Category 2: Halloween","Halloween Effect":"Category 2: Halloween","Median Hat Price":11.0},{"Name":"Shred Alert","Effect":"Ominous Night","Price":null,"Class":"All classes","Item Type":"Taunt","Equip Region":"Regular","Grade":"No Grade","Unboxed From":"Unusualifier","Robo":false,"Generation":"Halloween 2018","Effect Community Rating":3.21875,"Crate Cosmetic":false,"Months Since Last Price Update":-1,"Effect Median Price":28.5,"Hat Median Price":11.0,"Hat Rating":null,"Effect Rating":null,"Median Effect Rating":1.66875,"Median Hat Rating":0.1,"GradeSize":"No Grade","Robo\/Misc\/Not":"Regular","Type of Crate Temp":false,"Type of Crate":"Category 2: Other Series","Crate Unboxed From":"Unusualifier","Halloween":"Category 2: Halloween","Halloween Effect":"Category 2: Halloween","Median Hat Price":11.0},{"Name":"Shred Alert","Effect":"'72","Price":7.0,"Class":"All classes","Item Type":"Taunt","Equip Region":"Regular","Grade":"No Grade","Unboxed From":"Unusualifier","Robo":false,"Generation":"Love & War","Effect Community Rating":1.875,"Crate Cosmetic":false,"Months Since Last Price Update":2,"Effect Median Price":7.0,"Hat Median Price":11.0,"Hat Rating":0.0,"Effect Rating":-0.4,"Median Effect Rating":-0.225,"Median Hat Rating":0.1,"GradeSize":"No Grade","Robo\/Misc\/Not":"Regular","Type of Crate Temp":false,"Type of Crate":"Category 2: Other Series","Crate Unboxed From":"Unusualifier","Halloween":"Category 1: Regular","Halloween Effect":"Category 1: Regular","Median Hat Price":11.0},{"Name":"Shred Alert","Effect":"Fountain of Delight","Price":11.0,"Class":"All classes","Item Type":"Taunt","Equip Region":"Regular","Grade":"No Grade","Unboxed From":"Unusualifier","Robo":false,"Generation":"Love & War","Effect Community Rating":2.53125,"Crate Cosmetic":false,"Months Since Last Price Update":7,"Effect Median Price":10.75,"Hat Median Price":11.0,"Hat Rating":0.025,"Effect Rating":0.0,"Median Effect Rating":0.0,"Median Hat Rating":0.1,"GradeSize":"No Grade","Robo\/Misc\/Not":"Regular","Type of Crate Temp":false,"Type of Crate":"Category 2: Other Series","Crate Unboxed From":"Unusualifier","Halloween":"Category 1: Regular","Halloween Effect":"Category 1: Regular","Median Hat Price":11.0},{"Name":"Shred Alert","Effect":"Holy Grail","Price":10.5,"Class":"All classes","Item Type":"Taunt","Equip Region":"Regular","Grade":"No Grade","Unboxed From":"Unusualifier","Robo":false,"Generation":"Love & War","Effect Community Rating":2.90625,"Crate Cosmetic":false,"Months Since Last Price Update":8,"Effect Median Price":9.5,"Hat Median Price":11.0,"Hat Rating":0.1,"Effect Rating":-0.05,"Median Effect Rating":-0.05,"Median Hat Rating":0.1,"GradeSize":"No Grade","Robo\/Misc\/Not":"Regular","Type of Crate Temp":false,"Type of Crate":"Category 2: Other Series","Crate Unboxed From":"Unusualifier","Halloween":"Category 1: Regular","Halloween Effect":"Category 1: Regular","Median Hat Price":11.0},{"Name":"Shred Alert","Effect":"Mega Strike","Price":11.0,"Class":"All classes","Item Type":"Taunt","Equip Region":"Regular","Grade":"No Grade","Unboxed From":"Unusualifier","Robo":false,"Generation":"Love & War","Effect Community Rating":1.21875,"Crate Cosmetic":false,"Months Since Last Price Update":11,"Effect Median Price":7.375,"Hat Median Price":11.0,"Hat Rating":0.3625,"Effect Rating":0.0,"Median Effect Rating":-0.275,"Median Hat Rating":0.1,"GradeSize":"No Grade","Robo\/Misc\/Not":"Regular","Type of Crate Temp":false,"Type of Crate":"Category 2: Other Series","Crate Unboxed From":"Unusualifier","Halloween":"Category 1: Regular","Halloween Effect":"Category 1: Regular","Median Hat Price":11.0},{"Name":"Shred Alert","Effect":"Midnight Whirlwind","Price":8.0,"Class":"All classes","Item Type":"Taunt","Equip Region":"Regular","Grade":"No Grade","Unboxed From":"Unusualifier","Robo":false,"Generation":"Love & War","Effect Community Rating":0.46875,"Crate Cosmetic":false,"Months Since Last Price Update":11,"Effect Median Price":6.25,"Hat Median Price":11.0,"Hat Rating":0.175,"Effect Rating":-0.3,"Median Effect Rating":-0.3,"Median Hat Rating":0.1,"GradeSize":"No Grade","Robo\/Misc\/Not":"Regular","Type of Crate Temp":false,"Type of Crate":"Category 2: Other Series","Crate Unboxed From":"Unusualifier","Halloween":"Category 1: Regular","Halloween Effect":"Category 1: Regular","Median Hat Price":11.0},{"Name":"Shred Alert","Effect":"Screaming Tiger","Price":12.0,"Class":"All classes","Item Type":"Taunt","Equip Region":"Regular","Grade":"No Grade","Unboxed From":"Unusualifier","Robo":false,"Generation":"Love & War","Effect Community Rating":2.4375,"Crate Cosmetic":false,"Months Since Last Price Update":3,"Effect Median Price":10.5,"Hat Median Price":11.0,"Hat Rating":0.15,"Effect Rating":0.1,"Median Effect Rating":-0.0125,"Median Hat Rating":0.1,"GradeSize":"No Grade","Robo\/Misc\/Not":"Regular","Type of Crate Temp":false,"Type of Crate":"Category 2: Other Series","Crate Unboxed From":"Unusualifier","Halloween":"Category 1: Regular","Halloween Effect":"Category 1: Regular","Median Hat Price":11.0},{"Name":"Shred Alert","Effect":"Showstopper","Price":11.0,"Class":"All classes","Item Type":"Taunt","Equip Region":"Regular","Grade":"No Grade","Unboxed From":"Unusualifier","Robo":false,"Generation":"Love & War","Effect Community Rating":2.21875,"Crate Cosmetic":false,"Months Since Last Price Update":1,"Effect Median Price":9.125,"Hat Median Price":11.0,"Hat Rating":0.1875,"Effect Rating":0.0,"Median Effect Rating":-0.13125,"Median Hat Rating":0.1,"GradeSize":"No Grade","Robo\/Misc\/Not":"Regular","Type of Crate Temp":false,"Type of Crate":"Category 2: Other Series","Crate Unboxed From":"Unusualifier","Halloween":"Category 1: Regular","Halloween Effect":"Category 1: Regular","Median Hat Price":11.0},{"Name":"Shred Alert","Effect":"Silver Cyclone","Price":5.75,"Class":"All classes","Item Type":"Taunt","Equip Region":"Regular","Grade":"No Grade","Unboxed From":"Unusualifier","Robo":false,"Generation":"Love & War","Effect Community Rating":0.71875,"Crate Cosmetic":false,"Months Since Last Price Update":2,"Effect Median Price":5.75,"Hat Median Price":11.0,"Hat Rating":0.0,"Effect Rating":-0.525,"Median Effect Rating":-0.45,"Median Hat Rating":0.1,"GradeSize":"No Grade","Robo\/Misc\/Not":"Regular","Type of Crate Temp":false,"Type of Crate":"Category 2: Other Series","Crate Unboxed From":"Unusualifier","Halloween":"Category 1: Regular","Halloween Effect":"Category 1: Regular","Median Hat Price":11.0},{"Name":"Shred Alert","Effect":"Skill Gotten Gains","Price":13.0,"Class":"All classes","Item Type":"Taunt","Equip Region":"Regular","Grade":"No Grade","Unboxed From":"Unusualifier","Robo":false,"Generation":"Love & War","Effect Community Rating":0.84375,"Crate Cosmetic":false,"Months Since Last Price Update":11,"Effect Median Price":7.25,"Hat Median Price":11.0,"Hat Rating":0.575,"Effect Rating":0.2,"Median Effect Rating":-0.21875,"Median Hat Rating":0.1,"GradeSize":"No Grade","Robo\/Misc\/Not":"Regular","Type of Crate Temp":false,"Type of Crate":"Category 2: Other Series","Crate Unboxed From":"Unusualifier","Halloween":"Category 1: Regular","Halloween Effect":"Category 1: Regular","Median Hat Price":11.0}]